ory_oathkeeper_client/__init__.py
ory_oathkeeper_client/api_client.py
ory_oathkeeper_client/api_response.py
ory_oathkeeper_client/configuration.py
ory_oathkeeper_client/exceptions.py
ory_oathkeeper_client/py.typed
ory_oathkeeper_client/rest.py
ory_oathkeeper_client/api/__init__.py
ory_oathkeeper_client/api/api_api.py
ory_oathkeeper_client/api/metadata_api.py
ory_oathkeeper_client/models/__init__.py
ory_oathkeeper_client/models/generic_error.py
ory_oathkeeper_client/models/get_version200_response.py
ory_oathkeeper_client/models/health_not_ready_status.py
ory_oathkeeper_client/models/health_status.py
ory_oathkeeper_client/models/is_alive200_response.py
ory_oathkeeper_client/models/is_ready503_response.py
ory_oathkeeper_client/models/json_web_key.py
ory_oathkeeper_client/models/json_web_key_set.py
ory_oathkeeper_client/models/rule.py
ory_oathkeeper_client/models/rule_handler.py
ory_oathkeeper_client/models/rule_match.py
ory_oathkeeper_client/models/upstream.py
ory_oathkeeper_client/models/version.py
ory_oathkeeper_client-25.4.0.dist-info/LICENSE
ory_oathkeeper_client-25.4.0.dist-info/METADATA
ory_oathkeeper_client-25.4.0.dist-info/WHEEL
ory_oathkeeper_client-25.4.0.dist-info/top_level.txt
ory_oathkeeper_client-25.4.0.dist-info/RECORD
