Metadata-Version: 2.1
Name: ory-oathkeeper-client
Version: 25.4.0
Summary: Ory Oathkeeper API
Home-page: https://github.com/ory/sdk
Author: OpenAPI Generator community
Author-email: hi@ory.sh
License: Apache 2.0
Keywords: OpenAPI,OpenAPI-Generator,Ory Oathkeeper API
License-File: LICENSE
Requires-Dist: pydantic>=2
Requires-Dist: python-dateutil>=2.8.2
Requires-Dist: typing-extensions>=4.7.1
Requires-Dist: urllib3<3.0.0,>=1.25.3
